defichain/__init__.py
defichain/logger.py
defichain/exceptions/__init__.py
defichain/exceptions/hdwallet/DerivationError.py
defichain/exceptions/hdwallet/__init__.py
defichain/exceptions/http/BadMethod.py
defichain/exceptions/http/BadRequest.py
defichain/exceptions/http/Forbidden.py
defichain/exceptions/http/HTTPStatusCode.py
defichain/exceptions/http/InternalServerError.py
defichain/exceptions/http/NotFound.py
defichain/exceptions/http/RPCErrorCode.py
defichain/exceptions/http/ServiceUnavailable.py
defichain/exceptions/http/Unauthorized.py
defichain/exceptions/http/UnprocessableEntity.py
defichain/exceptions/http/WrongParmeters.py
defichain/exceptions/http/__init__.py
defichain/exceptions/transactions/__init__.py
defichain/exceptions/transactions/addresserror.py
defichain/exceptions/transactions/defitxerror.py
defichain/exceptions/transactions/deserializeerror.py
defichain/exceptions/transactions/inputerror.py
defichain/exceptions/transactions/keyerror.py
defichain/exceptions/transactions/notsupported.py
defichain/exceptions/transactions/rawtransactionerror.py
defichain/exceptions/transactions/tokenerror.py
defichain/exceptions/transactions/txbuildererror.py
defichain/exceptions/transactions/verifyerror.py
defichain/hdwallet/__init__.py
defichain/hdwallet/account.py
defichain/hdwallet/derivations.py
defichain/hdwallet/utils.py
defichain/hdwallet/wallet.py
defichain/libs/base58.py
defichain/libs/bech32.py
defichain/libs/ecc.py
defichain/libs/ripemd160.py
defichain/mnemonic/__init__.py
defichain/mnemonic/mnemonic.py
defichain/mnemonic/wordlist/__init__.py
defichain/mnemonic/wordlist/chinese_simplified.txt
defichain/mnemonic/wordlist/chinese_traditional.txt
defichain/mnemonic/wordlist/english.txt
defichain/mnemonic/wordlist/french.txt
defichain/mnemonic/wordlist/italian.txt
defichain/mnemonic/wordlist/japanese.txt
defichain/mnemonic/wordlist/korean.txt
defichain/mnemonic/wordlist/spanish.txt
defichain/networks/__init__.py
defichain/networks/networks.py
defichainTest-0.0.1b1.dist-info/LICENSE
defichainTest-0.0.1b1.dist-info/METADATA
defichainTest-0.0.1b1.dist-info/WHEEL
defichainTest-0.0.1b1.dist-info/top_level.txt
defichainTest-0.0.1b1.dist-info/RECORD
